MANIFEST.in
README.md
setup.py
lib/lg_shell/__init__.py
lib/lg_shell/main.py
lib/lg_shell.egg-info/PKG-INFO
lib/lg_shell.egg-info/SOURCES.txt
lib/lg_shell.egg-info/dependency_links.txt
lib/lg_shell.egg-info/entry_points.txt
lib/lg_shell.egg-info/top_level.txt
lib/lg_shell/cfg/config.json
lib/lg_shell/framework/__init__.py
lib/lg_shell/framework/abstract_config_data.py
lib/lg_shell/framework/config_data_interface.py
lib/lg_shell/framework/json_config_data.py
lib/lg_shell/framework/module_interface.py
lib/lg_shell/modules/__init__.py
lib/lg_shell/modules/abstract_module.py
lib/lg_shell/modules/config.py
lib/lg_shell/modules/install.py
lib/lg_shell/modules/keyboard_manager.py
lib/lg_shell/modules/module_factory.py
lib/lg_shell/modules/module_manager.py
lib/lg_shell/modules/setup.py
lib/lg_shell/modules/update.py
lib/lg_shell/resources/.bash_aliases
lib/lg_shell/resources/.bash_profile
lib/lg_shell/resources/.bashrc
lib/lg_shell/resources/.tmux.conf
lib/lg_shell/resources/.vim/vimrc
lib/lg_shell/resources/xkb_configs/pc_cmd_ctrl_swapped
lib/lg_shell/resources/xkb_configs/pc_default
lib/lg_shell/resources/xkb_configs/macintosh_vndr/ch_default
lib/lg_shell/resources/xkb_configs/macintosh_vndr/ch_fixed
lib/lg_shell/resources/xkb_configs/macintosh_vndr/us_minus_slash_swapped