Metadata-Version: 2.1
Name: lg-shell
Version: 0.0.0a3
Summary: A command line utility for systems setup
Home-page: https://github.com/lgulich/lgshell
Author: Lionel Gulich
Author-email: lgulich@ethz.ch
License: GPL-3.0
Download-URL: https://github.com/lgulich/lg-shell/archive/v0.0.alpha3.tar.gz
Platform: UNKNOWN
Classifier: Programming Language :: Python :: 3 :: Only
Classifier: License :: OSI Approved :: GNU General Public License v3 (GPLv3)
Classifier: Operating System :: POSIX :: Linux
Classifier: Operating System :: MacOS :: MacOS X
Classifier: Development Status :: 3 - Alpha
Classifier: Natural Language :: English
Requires-Python: >=3.5
